rtl/rat.v
`timescale 1ns/1ns
module rat 
(
    input           i_clk,
    input           i_rstn,

    input           i_rob_valid,
    input   [1:0]   i_rob_addr,
    input   [1:0]   i_rob_dst_addr,

    input           i_rs_req,
    input   [1:0]   i_rs_addr,

    output          o_rs_tag_valid,
    output  [1:0]   o_rs_tag,
    output          o_rs_val_valid,
    output  [15:0]  o_rs_val
);
reg             physical_reg_file_valid [0:3]; // 4個physical reg file的valid bit
reg     [1:0]   physical_reg_file       [0:3]; // 4個2bit的physical reg file，目前是4個arf跟4個prf，所以是2bit
reg     [15:0]  architecture_reg_file   [0:3]; // 4個16bit的architecture reg file，因為是放value，所以有16bit

genvar i;

generate
    for(i = 0; i < 4; i = i + 1)begin
        // prf[i].rob
        always @( posedge i_clk or negedge i_rstn ) begin
            if (!i_rstn) begin
                physical_reg_file[i] <= 'h0;
            end 
            else if(i_rob_valid & i_rob_dst_addr == i) begin
                physical_reg_file[i] <= i_rob_addr;
            end 
            else begin
                physical_reg_file[i] <= physical_reg_file[i];
            end
        end

        // prf[i].valid. After instruction retired, valid would change like 1 -> 0.
        always @( posedge i_clk or negedge i_rstn ) begin
            if (!i_rstn) begin
                physical_reg_file_valid[i] <= 'b0;
            end 
            else if(i_rob_valid & i_rob_dst_addr == i) begin
                physical_reg_file_valid[i] <= 'b1;
            end 
            else begin
                physical_reg_file_valid[i] <= physical_reg_file_valid[i];
            end
        end
    end
endgenerate

assign o_rs_tag_valid = i_rs_req & physical_reg_file_valid[i_rs_addr] == 1;
assign o_rs_tag = physical_reg_file[i_rs_addr];
assign o_rs_val_valid = i_rs_req & physical_reg_file_valid[i_rs_addr] == 0;
assign o_rs_val = architecture_reg_file[i_rs_addr];

// arf[i].rob
always @( posedge i_clk or negedge i_rstn ) begin
    if (!i_rstn) begin
        architecture_reg_file[0] <= 'h5;
        architecture_reg_file[1] <= 'h3;
        architecture_reg_file[2] <= 'h6;
        architecture_reg_file[3] <= 'h9;
    end 
    else begin
        architecture_reg_file[0] <= architecture_reg_file[0];
    end
end

endmodule

sim/tb_rat.v
`timescale 1ns/1ns

module tb_rat ();

reg         i_clk;
reg         i_rstn;
reg         i_rob_valid;
reg [1:0]   i_rob_addr;
reg [1:0]   i_rob_dst_addr;

reg         i_rs_req;
reg [1:0]   i_rs_addr;

wire            o_rs_tag_valid;
wire    [1:0]   o_rs_tag;
wire            o_rs_val_valid;
wire    [15:0]  o_rs_val;

wire        ooo;

rat dut (
    .i_clk          (i_clk ), 
    .i_rstn         (i_rstn ), 
    .i_rob_valid    (i_rob_valid),
    .i_rob_addr     (i_rob_addr),
    .i_rob_dst_addr (i_rob_dst_addr),

    .i_rs_req       (i_rs_req),
    .i_rs_addr      (i_rs_addr),

    .o_rs_tag_valid (o_rs_tag_valid),
    .o_rs_tag       (o_rs_tag),
    .o_rs_val_valid (o_rs_val_valid),
    .o_rs_val       (o_rs_val)
);

initial begin
    $dumpfile("waveform.vcd");
    $dumpvars(0);
    #500 $finish;
end

integer i;

initial begin
    for(i = 0; i < 4; i = i + 1) begin
        $dumpvars(0,dut.physical_reg_file_valid[i]);
        $dumpvars(0,dut.physical_reg_file[i]);
    end
end

always #5 i_clk = ~i_clk;

initial begin
    #0 
    i_clk  = 0;
    i_rstn = 1;
    i_rob_valid = 0;
    i_rob_addr = 0;
    i_rob_dst_addr = 0;
    #55
    i_rstn = 0;
    #50
    i_rstn = 1;
    #30
    rob_wr(3,0);
    #20
    rob_wr(1,0);
    #20
    rob_wr(2,3);
    #100
    rs_req(0);
    #20
    rs_req(1);
end

//==========================================================================
//==    task: rob_wr
//==========================================================================
task rob_wr;
    input   [1:0] rob_addr;
    input   [1:0] rob_dst_addr;
   
    begin
        @(posedge i_clk)
        i_rob_valid     <= 1;
        i_rob_addr      <= rob_addr;
        i_rob_dst_addr  <= rob_dst_addr;

        @(posedge i_clk)
        i_rob_valid     <= 0;
    end
endtask

//==========================================================================
//==    task: rs_req
//==========================================================================
task rs_req;
    input   [1:0] rs_addr;
   
    begin
        @(posedge i_clk)
        i_rs_req    <= 1;
        i_rs_addr   <= rs_addr;

        @(posedge i_clk)
        i_rs_req     <= 0;
    end
endtask

endmodule

sim/waveform.vcd
$date
	Mon Jul 29 15:22:40 2024
$end
$version
	Icarus Verilog
$end
$timescale
	1ns
$end
$scope module tb_rat $end
$var wire 1 ! o_rs_val_valid $end
$var wire 16 " o_rs_val [15:0] $end
$var wire 1 # o_rs_tag_valid $end
$var wire 2 $ o_rs_tag [1:0] $end
$var reg 1 % i_clk $end
$var reg 2 & i_rob_addr [1:0] $end
$var reg 2 ' i_rob_dst_addr [1:0] $end
$var reg 1 ( i_rob_valid $end
$var reg 2 ) i_rs_addr [1:0] $end
$var reg 1 * i_rs_req $end
$var reg 1 + i_rstn $end
$var integer 32 , i [31:0] $end
$scope module dut $end
$var wire 1 % i_clk $end
$var wire 2 - i_rob_addr [1:0] $end
$var wire 2 . i_rob_dst_addr [1:0] $end
$var wire 1 ( i_rob_valid $end
$var wire 2 / i_rs_addr [1:0] $end
$var wire 1 * i_rs_req $end
$var wire 1 + i_rstn $end
$var wire 2 0 o_rs_tag [1:0] $end
$var wire 1 # o_rs_tag_valid $end
$var wire 16 1 o_rs_val [15:0] $end
$var wire 1 ! o_rs_val_valid $end
$scope begin genblk1[0] $end
$upscope $end
$scope begin genblk1[1] $end
$upscope $end
$scope begin genblk1[2] $end
$upscope $end
$scope begin genblk1[3] $end
$upscope $end
$upscope $end
$scope task rob_wr $end
$var reg 2 2 rob_addr [1:0] $end
$var reg 2 3 rob_dst_addr [1:0] $end
$upscope $end
$scope task rs_req $end
$var reg 2 4 rs_addr [1:0] $end
$upscope $end
$upscope $end
$scope module tb_rat $end
$scope module dut $end
$var reg 1 5 \physical_reg_file_valid[0] $end
$upscope $end
$upscope $end
$scope module tb_rat $end
$scope module dut $end
$var reg 2 6 \physical_reg_file[0] [1:0] $end
$upscope $end
$upscope $end
$scope module tb_rat $end
$scope module dut $end
$var reg 1 7 \physical_reg_file_valid[1] $end
$upscope $end
$upscope $end
$scope module tb_rat $end
$scope module dut $end
$var reg 2 8 \physical_reg_file[1] [1:0] $end
$upscope $end
$upscope $end
$scope module tb_rat $end
$scope module dut $end
$var reg 1 9 \physical_reg_file_valid[2] $end
$upscope $end
$upscope $end
$scope module tb_rat $end
$scope module dut $end
$var reg 2 : \physical_reg_file[2] [1:0] $end
$upscope $end
$upscope $end
$scope module tb_rat $end
$scope module dut $end
$var reg 1 ; \physical_reg_file_valid[3] $end
$upscope $end
$upscope $end
$scope module tb_rat $end
$scope module dut $end
$var reg 2 < \physical_reg_file[3] [1:0] $end
$upscope $end
$upscope $end
$enddefinitions $end
#0
$dumpvars
bx <
x;
bx :
x9
bx 8
x7
bx 6
x5
bx 4
bx 3
bx 2
bx 1
bx 0
bx /
b0 .
b0 -
b100 ,
1+
x*
bx )
0(
b0 '
b0 &
0%
bx $
x#
bx "
x!
$end
#5
bx 6
x5
bx 8
x7
bx :
x9
bx <
x;
1%
#10
0%
#15
x;
bx <
x9
bx :
x7
bx 8
x5
bx 6
1%
#20
0%
#25
bx 6
x5
bx 8
x7
bx :
x9
bx <
x;
1%
#30
0%
#35
x;
bx <
x9
bx :
x7
bx 8
x5
bx 6
1%
#40
0%
#45
bx 6
x5
bx 8
x7
bx :
x9
bx <
x;
1%
#50
0%
#55
0;
b0 <
09
b0 :
07
b0 8
05
b0 6
1%
0+
#60
0%
#65
b0 6
05
b0 8
07
b0 :
09
b0 <
0;
1%
#70
0%
#75
0;
b0 <
09
b0 :
07
b0 8
05
b0 6
1%
#80
0%
#85
b0 6
05
b0 8
07
b0 :
09
b0 <
0;
1%
#90
0%
#95
0;
b0 <
09
b0 :
07
b0 8
05
b0 6
1%
#100
0%
#105
b0 6
05
b0 8
07
b0 :
09
b0 <
0;
1%
1+
#110
0%
#115
0;
b0 <
09
b0 :
07
b0 8
05
b0 6
1%
#120
0%
#125
b0 6
05
b0 8
07
b0 :
09
b0 <
0;
1%
#130
0%
#135
0;
b0 <
09
b0 :
07
b0 8
05
b0 6
b11 &
b11 -
1(
1%
b0 3
b11 2
#140
0%
#145
b11 6
15
b0 8
07
b0 :
09
b0 <
0;
0(
1%
#150
0%
#155
0;
b0 <
09
b0 :
07
b0 8
15
b11 6
1%
#160
0%
#165
b11 6
15
b0 8
07
b0 :
09
b0 <
0;
b1 &
b1 -
1(
1%
b1 2
#170
0%
#175
0;
b0 <
09
b0 :
07
b0 8
15
b1 6
0(
1%
#180
0%
#185
b1 6
15
b0 8
07
b0 :
09
b0 <
0;
1%
#190
0%
#195
0;
b0 <
09
b0 :
07
b0 8
15
b1 6
b11 '
b11 .
b10 &
b10 -
1(
1%
b11 3
b10 2
#200
0%
#205
b1 6
15
b0 8
07
b0 :
09
b10 <
1;
0(
1%
#210
0%
#215
1;
b10 <
09
b0 :
07
b0 8
15
b1 6
1%
#220
0%
#225
b1 6
15
b0 8
07
b0 :
09
b10 <
1;
1%
#230
0%
#235
1;
b10 <
09
b0 :
07
b0 8
15
b1 6
1%
#240
0%
#245
b1 6
15
b0 8
07
b0 :
09
b10 <
1;
1%
#250
0%
#255
1;
b10 <
09
b0 :
07
b0 8
15
b1 6
1%
#260
0%
#265
b1 6
15
b0 8
07
b0 :
09
b10 <
1;
1%
#270
0%
#275
1;
b10 <
09
b0 :
07
b0 8
15
b1 6
1%
#280
0%
#285
b1 6
15
b0 8
07
b0 :
09
b10 <
1;
1%
#290
0%
#295
1;
b10 <
09
b0 :
07
b0 8
15
b1 6
1%
#300
0%
#305
1#
0!
b1 6
15
b0 8
07
b0 :
09
b10 <
1;
b1 $
b1 0
b101 "
b101 1
b0 )
b0 /
1*
1%
b0 4
#310
0%
#315
0#
1;
b10 <
09
b0 :
07
b0 8
15
b1 6
0*
1%
#320
0%
#325
b1 6
15
b0 8
07
b0 :
09
b10 <
1;
1%
#330
0%
#335
1!
1;
b10 <
09
b0 :
07
b0 8
15
b1 6
b0 $
b0 0
b11 "
b11 1
b1 )
b1 /
1*
1%
b1 4
#340
0%
#345
0!
b1 6
15
b0 8
07
b0 :
09
b10 <
1;
0*
1%
#350
0%
#355
1;
b10 <
09
b0 :
07
b0 8
15
b1 6
1%
#360
0%
#365
b1 6
15
b0 8
07
b0 :
09
b10 <
1;
1%
#370
0%
#375
1;
b10 <
09
b0 :
07
b0 8
15
b1 6
1%
#380
0%
#385
b1 6
15
b0 8
07
b0 :
09
b10 <
1;
1%
#390
0%
#395
1;
b10 <
09
b0 :
07
b0 8
15
b1 6
1%
#400
0%
#405
b1 6
15
b0 8
07
b0 :
09
b10 <
1;
1%
#410
0%
#415
1;
b10 <
09
b0 :
07
b0 8
15
b1 6
1%
#420
0%
#425
b1 6
15
b0 8
07
b0 :
09
b10 <
1;
1%
#430
0%
#435
1;
b10 <
09
b0 :
07
b0 8
15
b1 6
1%
#440
0%
#445
b1 6
15
b0 8
07
b0 :
09
b10 <
1;
1%
#450
0%
#455
1;
b10 <
09
b0 :
07
b0 8
15
b1 6
1%
#460
0%
#465
b1 6
15
b0 8
07
b0 :
09
b10 <
1;
1%
#470
0%
#475
1;
b10 <
09
b0 :
07
b0 8
15
b1 6
1%
#480
0%
#485
b1 6
15
b0 8
07
b0 :
09
b10 <
1;
1%
#490
0%
#495
1;
b10 <
09
b0 :
07
b0 8
15
b1 6
1%
